app.py
pycompound/build_library.py
pycompound/plot_spectra.py
pycompound/plot_spectra_CLI.py
pycompound/processing.py
pycompound/similarity_measures.py
pycompound/spec_lib_matching.py
pycompound/spec_lib_matching_CLI.py
pycompound/tuning_CLI_DE.py
pycompound/tuning_CLI_grid.py
pycompound-0.1.7.dist-info/licenses/LICENSE
pycompound-0.1.7.dist-info/METADATA
pycompound-0.1.7.dist-info/WHEEL
pycompound-0.1.7.dist-info/top_level.txt
pycompound-0.1.7.dist-info/RECORD
